mindrove/__init__.py
mindrove/board_shim.py
mindrove/data_filter.py
mindrove/exit_codes.py
mindrove/ml_model.py
mindrove/utils.py
mindrove/lib/BoardController.dll
mindrove/lib/BoardController32.dll
mindrove/lib/DataHandler.dll
mindrove/lib/DataHandler32.dll
mindrove/lib/MLModule.dll
mindrove/lib/MindRoveWrapper.dll
mindrove/lib/libBoardController.dylib
mindrove/lib/libBoardController.so
mindrove/lib/libDataHandler.dylib
mindrove/lib/libDataHandler.so
mindrove/lib/libMLModule.dylib
mindrove/lib/libMLModule.so
mindrove/lib/libMindRoveWrapper.dylib
mindrove/lib/libMindRoveWrapper.so
mindrove/lib/aarch64/libBoardController.so
mindrove/lib/aarch64/libDataHandler.so
mindrove/lib/aarch64/libMLModule.so
mindrove/lib/aarch64/libMindRoveWrapper.so
mindrove/lib/arm32/libBoardController.so
mindrove/lib/arm32/libDataHandler.so
mindrove/lib/arm32/libMLModule.so
mindrove/lib/arm32/libMindRoveWrapper.so
mindrove-5.2.4.dist-info/LICENSE.txt
mindrove-5.2.4.dist-info/METADATA
mindrove-5.2.4.dist-info/WHEEL
mindrove-5.2.4.dist-info/top_level.txt
mindrove-5.2.4.dist-info/zip-safe
mindrove-5.2.4.dist-info/RECORD
