Metadata-Version: 2.1
Name: mindrove
Version: 5.2.4
Summary: Python Binding for MindRove
Home-page: https://github.com/MindRove/MindRoveSDK
Author: Mindrove
Author-email: info@mindrove.com
License: UNKNOWN
Platform: UNKNOWN
Requires-Python: >=3.5.6
License-File: LICENSE.txt
Requires-Dist: numpy
Requires-Dist: setuptools
